README.rst
setup.py
albums_plugin/__init__.py
albums_plugin/admin.py
albums_plugin/cms_plugins.py
albums_plugin/factories.py
albums_plugin/models.py
albums_plugin/tests.py
albums_plugin/views.py
albums_plugin/migrations/0001_initial.py
albums_plugin/migrations/0002_auto_20151021_1104.py
albums_plugin/migrations/0003_auto_20151021_1106.py
albums_plugin/migrations/0004_albumsplugin.py
albums_plugin/migrations/0005_albumupload.py
albums_plugin/migrations/0006_photo_thumb.py
albums_plugin/migrations/__init__.py
djangocms_albums_plugin.egg-info/PKG-INFO
djangocms_albums_plugin.egg-info/SOURCES.txt
djangocms_albums_plugin.egg-info/dependency_links.txt
djangocms_albums_plugin.egg-info/not-zip-safe
djangocms_albums_plugin.egg-info/requires.txt
djangocms_albums_plugin.egg-info/top_level.txt